{
  "app": 358080,
  "device_id": "6ff20180-8dd3-4a81-8bff-6270dba529a8",
  "user_id": null,
  "client_event_time": "2022-01-11 10:02:23.085000",
  "event_id": 963956373,
  "session_id": -1,
  "event_type": "Loaded a Page",
  "amplitude_event_type": null,
  "version_name": null,
  "platform": "Web",
  "os_name": "Safari",
  "os_version": "15",
  "device_brand": null,
  "device_manufacturer": null,
  "device_model": "Mac OS",
  "device_family": "Mac OS",
  "device_type": null,
  "device_carrier": null,
  "location_lat": null,
  "location_lng": null,
  "ip_address": "172.226.50.20",
  "country": "Russia",
  "language": "Russian",
  "library": "segment",
  "city": "Moscow",
  "region": "Moscow",
  "dma": null,
  "event_properties": {
    "url": "https:\/\/www.attributionapp.com\/privacy\/",
    "title": "Privacy - Attribution",
    "referrer": "https:\/\/www.google.ru\/",
    "path": "\/privacy\/"
  },
  "user_properties": {},
  "global_user_properties": {},
  "group_properties": {},
  "event_time": "2022-01-11 10:02:23.085000",
  "client_upload_time": "2022-01-11 10:02:24.798000",
  "server_upload_time": "2022-01-11 10:02:24.802000",
  "server_received_time": "2022-01-11 10:02:24.798000",
  "amplitude_id": 346630956846,
  "idfa": null,
  "adid": null,
  "data": {},
  "paying": null,
  "start_version": null,
  "user_creation_time": "2022-01-11 10:02:23.085000",
  "uuid": "94fd9096-72c5-11ec-8424-0a0503ad65cb",
  "groups": {},
  "sample_rate": null,
  "$insert_id": "ajs-next-2ffc90cac120b9380635a28b1e8edc87:3umdysnl7k-1",
  "$insert_key": "01aa838757698aa037e6dba93735cd4797#869",
  "is_attribution_event": false,
  "amplitude_attribution_ids": null,
  "plan": {},
  "partner_id": null,
  "$schema": 13,
  "processed_time": "2022-01-11 10:02:27.712360"
}
